compresion_zip/__init__.py
compresion_zip/__main__.py
compresion_zip/comprecion_descomprecion_zip.py
compresion_zip-1.1.0.dist-info/licenses/LICENSE
compresion_zip-1.1.0.dist-info/METADATA
compresion_zip-1.1.0.dist-info/WHEEL
compresion_zip-1.1.0.dist-info/entry_points.txt
compresion_zip-1.1.0.dist-info/top_level.txt
compresion_zip-1.1.0.dist-info/RECORD
