Metadata-Version: 2.4
Name: compresion_zip
Version: 1.1.0
Summary: Compresor y descompresor ZIP con barra de progreso y CLI
Author: Tu Nombre
License: MIT
Requires-Python: >=3.8
License-File: LICENSE
Requires-Dist: tqdm
Dynamic: author
Dynamic: license-file
Dynamic: requires-dist
Dynamic: requires-python
Dynamic: summary
